<annotation>
	<folder>without</folder>
	<filename>e106.JPG</filename>
	<path>C:\Users\ADETAYO\Desktop\Design\emekapics\image_with_mask\without\e106.JPG</path>
	<source>
		<database>Unknown</database>
	</source>
	<size>
		<width>255</width>
		<height>284</height>
		<depth>3</depth>
	</size>
	<segmented>0</segmented>
	<object>
		<name>without_facemask</name>
		<pose>Unspecified</pose>
		<truncated>0</truncated>
		<difficult>0</difficult>
		<bndbox>
			<xmin>31</xmin>
			<ymin>191</ymin>
			<xmax>120</xmax>
			<ymax>262</ymax>
		</bndbox>
	</object>
</annotation>
