<annotation>
	<folder>without</folder>
	<filename>e66.JPG</filename>
	<path>C:\Users\ADETAYO\Desktop\Design\emekapics\image_with_mask\without\e66.JPG</path>
	<source>
		<database>Unknown</database>
	</source>
	<size>
		<width>126</width>
		<height>191</height>
		<depth>3</depth>
	</size>
	<segmented>0</segmented>
	<object>
		<name>without_facemask</name>
		<pose>Unspecified</pose>
		<truncated>0</truncated>
		<difficult>0</difficult>
		<bndbox>
			<xmin>47</xmin>
			<ymin>99</ymin>
			<xmax>112</xmax>
			<ymax>155</ymax>
		</bndbox>
	</object>
</annotation>
