<annotation>
	<folder>crop_pic</folder>
	<filename>m7.jpg</filename>
	<path>C:\Users\ADETAYO\Desktop\Design\emekapics\image_with_mask\crop_pic\m7.jpg</path>
	<source>
		<database>Unknown</database>
	</source>
	<size>
		<width>480</width>
		<height>584</height>
		<depth>3</depth>
	</size>
	<segmented>0</segmented>
	<object>
		<name>with_facemask</name>
		<pose>Unspecified</pose>
		<truncated>0</truncated>
		<difficult>0</difficult>
		<bndbox>
			<xmin>157</xmin>
			<ymin>311</ymin>
			<xmax>430</xmax>
			<ymax>503</ymax>
		</bndbox>
	</object>
</annotation>
